patlas.cp310-win32.pyd
_patlas/__init__.py
_patlas/util.py
patlas-0.0.6.dist-info/LICENSE
patlas-0.0.6.dist-info/METADATA
patlas-0.0.6.dist-info/WHEEL
patlas-0.0.6.dist-info/entry_points.txt
patlas-0.0.6.dist-info/top_level.txt
patlas-0.0.6.dist-info/RECORD
