Metadata-Version: 2.1
Name: patlas
Version: 0.0.6
Summary: Simple texture atlas packer
Home-page: https://github.com/aforren1/patlas
Author: Alex Forrence
Author-email: alex.forrence@gmail.com
License: UNKNOWN
Platform: UNKNOWN
Classifier: Programming Language :: Python :: 3
Classifier: License :: OSI Approved :: MIT License
Classifier: Operating System :: OS Independent
